add_server/__init__.py
add_server/__main__.py
add_server/add_server.py
add_server/config.json
add_server-0.1.0.dist-info/METADATA
add_server-0.1.0.dist-info/WHEEL
add_server-0.1.0.dist-info/entry_points.txt
add_server-0.1.0.dist-info/RECORD
