Metadata-Version: 2.4
Name: add-server
Version: 0.1.0
Summary: Add your description here
Author-email: Ashutoshsahu-13 <ashutoshsahu243@gmail.com>
Requires-Python: >=3.13
Requires-Dist: build>=1.2.2.post1
Requires-Dist: mcp[cli]>=1.11.0
Requires-Dist: twine>=6.1.0
